hull/__init__.py
hull/data/__init__.py
hull-0.0.1.dist-info/METADATA
hull-0.0.1.dist-info/WHEEL
hull-0.0.1.dist-info/top_level.txt
hull-0.0.1.dist-info/RECORD
