Metadata-Version: 2.1
Name: hull
Version: 0.0.1
Summary: hull
Home-page: https://github.com/gitvipin/hull
Author: Vipin Sharma
Author-email: sh.vipin@gmail.com
License: UNKNOWN
Platform: UNKNOWN
Classifier: Programming Language :: Python :: 3
Classifier: Operating System :: OS Independent
